LICENSE.txt
README.md
setup.py
linear_regression_ayoub_lab3/__init__.py
linear_regression_ayoub_lab3/model.py
linear_regression_ayoub_lab3.egg-info/PKG-INFO
linear_regression_ayoub_lab3.egg-info/SOURCES.txt
linear_regression_ayoub_lab3.egg-info/dependency_links.txt
linear_regression_ayoub_lab3.egg-info/requires.txt
linear_regression_ayoub_lab3.egg-info/top_level.txt