Metadata-Version: 2.4
Name: linear_regression_ayoub_lab3
Version: 1.0.0
Summary: Simple Linear Regression from scratch
Home-page: https://pypi.org/project/linear-regression-ayoub/
Author: Ayoub Aziba
Author-email: ma.aziba@esi-sba.dz
License: MIT
Requires-Python: >=3.7
License-File: LICENSE.txt
Requires-Dist: numpy
Dynamic: author
Dynamic: author-email
Dynamic: description
Dynamic: description-content-type
Dynamic: home-page
Dynamic: license
Dynamic: license-file
Dynamic: requires-dist
Dynamic: requires-python
Dynamic: summary
